find_and_check_hosts/__init__.py
find_and_check_hosts/checker.py
find_and_check_hosts/example-config.yaml
find_and_check_hosts/iana_tld_list.txt
find_and_check_hosts/main.py
find_and_check_hosts/patterns.py
find_and_check_hosts/replacer.py
find_and_check_hosts/rules.py
find_and_check_hosts-0.1.5.data/scripts/find-and-check-hosts
find_and_check_hosts-0.1.5.dist-info/LICENSE
find_and_check_hosts-0.1.5.dist-info/METADATA
find_and_check_hosts-0.1.5.dist-info/WHEEL
find_and_check_hosts-0.1.5.dist-info/top_level.txt
find_and_check_hosts-0.1.5.dist-info/RECORD
