Metadata-Version: 2.1
Name: find-and-check-hosts
Version: 0.1.5
Summary: Find hostnames and IPv4 addresses in text files and check them against a set of rules
Home-page: https://gitlab.com/six-two/find-and-check-hosts
Author: six-two
Author-email: pip@six-two.dev
License: MIT License
Classifier: License :: OSI Approved :: MIT License
Classifier: Operating System :: POSIX :: Linux
Classifier: Programming Language :: Python :: 3
Classifier: Programming Language :: Python :: 3.9
Classifier: Programming Language :: Python :: 3.10
Requires-Python: >=3.9
License-File: LICENSE
Requires-Dist: PyYAML >=5.4.0
Requires-Dist: schema >=0.7.0
Requires-Dist: termcolor >=1.1.0
